FixedSizeFileIOTools/__init__.py
FixedSizeFileIOTools/cli.py
FixedSizeFileIOTools/file_handler.py
FixedSizeFileIOTools/models.py
FixedSizeFileIOTools-1.2.dist-info/METADATA
FixedSizeFileIOTools-1.2.dist-info/WHEEL
FixedSizeFileIOTools-1.2.dist-info/top_level.txt
FixedSizeFileIOTools-1.2.dist-info/RECORD
