Metadata-Version: 2.1
Name: FixedSizeFileIOTools
Version: 1.2
Summary: Python library for handling fixed sized files, with interactive CLI
Author: Patryk Jaworski
Author-email: patrykjaworski9966@gmail.com
License: The Unlicense
Project-URL: Source, https://github.com/patrykjawor/FixedSizeFileIOTools
Requires-Python: >=3.12
Requires-Dist: pydantic
Requires-Dist: click
